algodata/__init__.py
algodata/datasets/__init__.py
algodata/datasets/candles.py
algodata/transforms/__init__.py
algodata/vis/__init__.py
algodata/vis/candles.py
algodata-0.0.0.dist-info/LICENSE
algodata-0.0.0.dist-info/METADATA
algodata-0.0.0.dist-info/WHEEL
algodata-0.0.0.dist-info/top_level.txt
algodata-0.0.0.dist-info/RECORD
