Metadata-Version: 2.1
Name: algodata
Version: 0.0.0
Summary: Tools for interacting with financial timeseries for algorithmic trading
Home-page: https://github.com/timesler/algodata
Author: Tim Esler
Author-email: tim.esler@gmail.com
License: UNKNOWN
Platform: UNKNOWN
Classifier: Programming Language :: Python :: 3
Classifier: License :: OSI Approved :: MIT License
Classifier: Operating System :: OS Independent
Requires-Python: >=3.6
Requires-Dist: numpy
Requires-Dist: pandas
Requires-Dist: attrdict
Requires-Dist: xt-training
Requires-Dist: dash
Requires-Dist: jupyter-dash
